LICENSE
README.md
setup.py
capp_ui/__init__.py
capp_ui/config.py
capp_ui/date_extend.py
capp_ui/device.py
capp_ui/dir.py
capp_ui/domain_service.py
capp_ui/fee.py
capp_ui/libs.py
capp_ui/mobile_terminals.py
capp_ui/platforms.py
capp_ui/test.py
capp_ui/uiautomation_proxy.py
capp_ui/utils.py
capp_ui/validators.py
ctrip_app_ui.egg-info/PKG-INFO
ctrip_app_ui.egg-info/SOURCES.txt
ctrip_app_ui.egg-info/dependency_links.txt
ctrip_app_ui.egg-info/requires.txt
ctrip_app_ui.egg-info/top_level.txt